pytgpt/__init__.py
pytgpt/__main__.py
pytgpt/async_providers.py
pytgpt/base.py
pytgpt/console.py
pytgpt/exceptions.py
pytgpt/utils.py
pytgpt/api/__init__.py
pytgpt/api/__main__.py
pytgpt/api/utils.py
pytgpt/api/v1.py
pytgpt/auto/__init__.py
pytgpt/auto/errors.py
pytgpt/auto/main.py
pytgpt/blackboxai/__init__.py
pytgpt/blackboxai/main.py
pytgpt/gpt4all/__init__.py
pytgpt/gpt4all/main.py
pytgpt/gpt4free/__init__.py
pytgpt/gpt4free/main.py
pytgpt/gpt4free/utils.py
pytgpt/groq/__init__.py
pytgpt/groq/main.py
pytgpt/imager/__init__.py
pytgpt/imager/imager.py
pytgpt/koboldai/__init__.py
pytgpt/koboldai/main.py
pytgpt/novita/__init__.py
pytgpt/novita/main.py
pytgpt/openai/__init__.py
pytgpt/openai/main.py
pytgpt/perplexity/__init__.py
pytgpt/perplexity/main.py
pytgpt/phind/__init__.py
pytgpt/phind/main.py
pytgpt/poe/__init__.py
pytgpt/poe/main.py
python_tgpt-0.8.0.dist-info/LICENSE
python_tgpt-0.8.0.dist-info/METADATA
python_tgpt-0.8.0.dist-info/WHEEL
python_tgpt-0.8.0.dist-info/entry_points.txt
python_tgpt-0.8.0.dist-info/top_level.txt
python_tgpt-0.8.0.dist-info/RECORD
