Metadata-Version: 2.1
Name: python-tgpt
Version: 0.8.0
Summary: Interact with AI without API key
Home-page: https://github.com/Simatwa/python-tgpt
Author: Smartwa
Author-email: simatwacaleb@proton.me
Maintainer: Smartwa
License: MIT
Project-URL: Bug Report, https://github.com/Simatwa/python-tgpt/issues/new
Project-URL: Homepage, https://github.com/Simatwa/python-tgpt
Project-URL: Source Code, https://github.com/Simatwa/python-tgpt
Project-URL: Issue Tracker, https://github.com/Simatwa/python-tgpt/issues
Project-URL: Download, https://github.com/Simatwa/python-tgpt/releases
Project-URL: Documentation, https://github.com/Simatwa/python-tgpt/blob/main/docs
Keywords: chatgpt,gpt,tgpt,pytgpt,chatgpt-cli,chatgpt-sdk,chatgpt-api,llama-api,leo,llama2,blackboxai,opengpt,koboldai,openai,bard,gpt4free,gpt4all-cli,gptcli,poe-api,perplexity,novita,gpt4free
Classifier: License :: OSI Approved :: MIT License
Classifier: Intended Audience :: Developers
Classifier: Natural Language :: English
Classifier: License :: Free For Home Use
Classifier: Intended Audience :: Customer Service
Classifier: Programming Language :: Python
Classifier: Topic :: Software Development :: Libraries :: Python Modules
Classifier: Topic :: Scientific/Engineering :: Artificial Intelligence
Classifier: Programming Language :: Python :: 3 :: Only
Classifier: Programming Language :: Python :: 3.10
Classifier: Programming Language :: Python :: 3.11
Classifier: Programming Language :: Python :: 3.12
Classifier: Programming Language :: Python :: 3.13
Requires-Python: >=3.10
License-File: LICENSE
Requires-Dist: requests[socks] >=2.32.3
Requires-Dist: appdirs ==1.4.4
Requires-Dist: pyyaml ==6.0.1
Requires-Dist: poe-api-wrapper ==1.7.0
Requires-Dist: brotli ==1.1.0
Requires-Dist: g4f >=0.3.3.3
Requires-Dist: Helpingai-T2 ==0.5
Requires-Dist: python-vlc >=3.0.20
Requires-Dist: httpx ==0.27.2
Provides-Extra: all
Requires-Dist: g4f[all] >=0.3.3.3 ; extra == 'all'
Requires-Dist: matplotlib ; extra == 'all'
Requires-Dist: gpt4all ==2.2.0 ; extra == 'all'
Requires-Dist: click ==8.1.3 ; extra == 'all'
Requires-Dist: rich ==13.3.4 ; extra == 'all'
Requires-Dist: clipman ==3.1.0 ; extra == 'all'
Requires-Dist: pyperclip ==1.8.2 ; extra == 'all'
Requires-Dist: colorama ==0.4.6 ; extra == 'all'
Requires-Dist: python-dotenv ==1.0.0 ; extra == 'all'
Requires-Dist: prompt-toolkit ==3.0.48 ; extra == 'all'
Requires-Dist: fastapi[all] ==0.115.4 ; extra == 'all'
Provides-Extra: api
Requires-Dist: fastapi[all] ==0.115.4 ; extra == 'api'
Provides-Extra: cli
Requires-Dist: click ==8.1.3 ; extra == 'cli'
Requires-Dist: rich ==13.3.4 ; extra == 'cli'
Requires-Dist: clipman ==3.1.0 ; extra == 'cli'
Requires-Dist: pyperclip ==1.8.2 ; extra == 'cli'
Requires-Dist: colorama ==0.4.6 ; extra == 'cli'
Requires-Dist: python-dotenv ==1.0.0 ; extra == 'cli'
Requires-Dist: prompt-toolkit ==3.0.48 ; extra == 'cli'
Provides-Extra: termux
Requires-Dist: g4f ==0.2.6.1 ; extra == 'termux'
Provides-Extra: termux-all
Requires-Dist: g4f ==0.2.6.1 ; extra == 'termux-all'
Requires-Dist: click ==8.1.3 ; extra == 'termux-all'
Requires-Dist: rich ==13.3.4 ; extra == 'termux-all'
Requires-Dist: clipman ==3.1.0 ; extra == 'termux-all'
Requires-Dist: pyperclip ==1.8.2 ; extra == 'termux-all'
Requires-Dist: colorama ==0.4.6 ; extra == 'termux-all'
Requires-Dist: python-dotenv ==1.0.0 ; extra == 'termux-all'
Requires-Dist: prompt-toolkit ==3.0.48 ; extra == 'termux-all'
Requires-Dist: fastapi[all] ==0.115.4 ; extra == 'termux-all'
Provides-Extra: termux-api
Requires-Dist: g4f ==0.2.6.1 ; extra == 'termux-api'
Requires-Dist: fastapi[all] ==0.115.4 ; extra == 'termux-api'
Provides-Extra: termux-cli
Requires-Dist: g4f ==0.2.6.1 ; extra == 'termux-cli'
Requires-Dist: click ==8.1.3 ; extra == 'termux-cli'
Requires-Dist: rich ==13.3.4 ; extra == 'termux-cli'
Requires-Dist: clipman ==3.1.0 ; extra == 'termux-cli'
Requires-Dist: pyperclip ==1.8.2 ; extra == 'termux-cli'
Requires-Dist: colorama ==0.4.6 ; extra == 'termux-cli'
Requires-Dist: python-dotenv ==1.0.0 ; extra == 'termux-cli'
Requires-Dist: prompt-toolkit ==3.0.48 ; extra == 'termux-cli'
